monstera/__init__.py
monstera/__main__.py
monstera/_core/__init__.py
monstera/_core/_entry_points.py
monstera/_core/_main.py
monstera/_core/_utils.py
monstera-0.0.5.dist-info/LICENSE.md
monstera-0.0.5.dist-info/METADATA
monstera-0.0.5.dist-info/WHEEL
monstera-0.0.5.dist-info/entry_points.txt
monstera-0.0.5.dist-info/top_level.txt
monstera-0.0.5.dist-info/RECORD
