Metadata-Version: 2.1
Name: monstera
Version: 0.0.5
Summary: A cross-platform CLI to quickly retrieve system information to make issue management easier.
Home-page: https://github.com/dishb/monstera
Author: Dishant B. (@dishb)
Author-email: code.dishb@gmail.com
License: MIT
Project-URL: Documentation, https://github.com/dishb/monstera/tree/main/docs
Project-URL: Source, https://github.com/dishb/monstera/
Project-URL: Issue Tracker, https://github.com/dishb/monstera/issues
Keywords: monstera,bug tracker,bug tracking,issue tracker,issue tracking,tool,developers,developing,monstera tool,dependencies,versions,file locations,python,cross-platform,python3
Classifier: Programming Language :: Python :: 3.9
Classifier: Programming Language :: Python :: 3.10
Classifier: Programming Language :: Python :: 3.11
Classifier: Operating System :: OS Independent
Classifier: License :: OSI Approved :: MIT License
Classifier: Environment :: Console
Classifier: Intended Audience :: Developers
Classifier: Natural Language :: English
Classifier: Topic :: Software Development
Classifier: Topic :: Software Development :: Bug Tracking
Classifier: Topic :: Software Development :: Libraries :: Python Modules
Requires-Python: >=3.9
License-File: LICENSE.md
Requires-Dist: distro
Requires-Dist: colorama
